{
      "\u9ed1\u864e\u6070\u59c6\u5e15\u74e6\u7279": 4,
      "\u9ed1\u864e": 4,
      "\u5967\u675c\u4e9e": 4,
      "\u6bba\u622e\u8005": 4,
      "\u9ed1\u86c7\u9a0e\u58eb\u5718\u9ea5\u80af": 4,
      "\u9ea5\u80af": 4,
      "\u5361\u723e\u8fea\u4fee": 4,
      "\u8725\u8734\u738b": 4,
      "\u5361\u738b": 4,
      "\u5361\u53f8\u7279\u738b": 4,
      "\u5c3c\u7f85\u5fb7": 4,
      "\u5c60\u6bba\u8005\u83ab\u5229\u63d0\u4e9e": 4,
      "\u83ab\u5229\u63d0\u4e9e": 4,
      "\u98db\u9f8d": 4,
      "\u5fb7\u96f7\u514b": 4,
      "\u4e7e\u6e34\u7684\u5fb7\u96f7\u514b": 4,
      "\u592b\u4eba": 4,
      "\u5df4\u723e\u535a\u85a9\u592b\u4eba": 4,
      "\u5927\u8173": 4,
      "\u6d77\u8cca\u738b": 4,
      "\u5be9\u5224\u8005\u62c9\u99ac\u4fee": 8,
      "\u5be9\u5224\u8005": 8,
      "\u62c9\u99ac\u4fee": 8,
      "\u86c7\u5973": 8,
      "\u5be9\u5224": 8,
      "\u5927\u9ed1": 8,
      "\u5927\u9ed1\u9577\u8005": 8,
      "\u70cf\u52d2": 8,
      "\u70cf\u52d2\u5eab\u65af": 8,
      "\u5948\u514b": 8,
      "\u5948\u514b\u504c\u65af": 8,
      "\u5948\u514b\u8afe\u65af": 8,
      "\u87fb\u540e": 8,
      "\u5de8\u87fb\u5973\u7687": 8,
      "\u5de8\u87fb\u5973\u738b": 8,
      "\u626d\u66f2\u7684\u827e\u5967\u7279": 8,
      "\u827e\u5967\u7279": 8,
      "\u626d\u66f2": 8,
      "\u514b\u6d1b\u6797": 8,
      "\u72fc\u738b": 8,
      "\u5eab\u723e\u8a17": 8,
      "\u54c8\u683c\u746a": 8,
      "\u9f8d\u738b": 8,
      "\u982d\u76ee\u54c8\u683c\u746a": 8,
      "\u56db\u8272": 12,
      "\u5de8\u4eba": 12,
      "test": 1,
      "\u99ac\u4fee": 8,
      "\u879e\u87fb": 8,
      "\u5c0f\u8309\u8389": 4,
      "\u7537\u5c60": 4,
      "\u7537\u5c60\u6bba": 4,
      "\u5973\u5c60": 4,
      "\u5973\u5c60\u6bba": 4,
      "\u6d77\u8cca": 4,
      "\u5361\u53f8\u7279": 4,
      "\u8725\u8734": 4,
      "\u5eab\u7d04": 6,
      "\u98db\u9f8d1": 4,
      "\u98db\u9f8d2": 4,
      "\u98db\u9f8d3": 4,
      "\u98db\u9f8d4": 4
}